langup/__init__.py
langup/base.py
langup/config.py
langup/api/QQ.py
langup/api/__init__.py
langup/api/wechat.py
langup/api/bcut_asr/__init__.py
langup/api/bcut_asr/__main__.py
langup/api/bcut_asr/orm.py
langup/api/bilibili/__init__.py
langup/api/bilibili/live.py
langup/api/bilibili/schema.py
langup/api/bilibili/session.py
langup/api/bilibili/video.py
langup/brain/__init__.py
langup/brain/agents/__init__.py
langup/brain/chains/__init__.py
langup/brain/chains/llm.py
langup/environment/__init__.py
langup/listener/__init__.py
langup/listener/bilibili.py
langup/listener/user.py
langup/reaction/__init__.py
langup/reaction/bilibili.py
langup/reaction/voice.py
langup/uploader/__init__.py
langup/uploader/bilibili.py
langup/uploader/simple.py
langup/utils/SOP.py
langup/utils/__init__.py
langup/utils/apps.py
langup/utils/consts.py
langup/utils/converts.py
langup/utils/enums.py
langup/utils/exceptions.py
langup/utils/filters.py
langup/utils/logger.py
langup/utils/mixins.py
langup/utils/thread.py
langup/utils/utils.py
langup/utils/vid_transform.py
langup-0.0.10.dist-info/LICENSE
langup-0.0.10.dist-info/METADATA
langup-0.0.10.dist-info/WHEEL
langup-0.0.10.dist-info/top_level.txt
langup-0.0.10.dist-info/RECORD
