Metadata-Version: 2.1
Name: langup
Version: 0.0.10
Summary: 社交网络机器人
Home-page: https://github.com/jiran214/langup-ai/tree/master
Author: ran
Author-email: jiran214@qq.com
Classifier: Programming Language :: Python :: 3
Classifier: License :: OSI Approved :: MIT License
Classifier: Operating System :: OS Independent
Requires-Python: >=3.8
License-File: LICENSE
Requires-Dist: edge-tts (==6.1.8)
Requires-Dist: bilibili-api-python (==16.1.0)
Requires-Dist: openai (==0.28.0)
Requires-Dist: langchain (==0.0.286)
Requires-Dist: ratelimit (==2.2.1)
Requires-Dist: pygame (~=2.5.1)
Requires-Dist: scipy (==1.7.3)
Requires-Dist: httpx (~=0.24.1)
Requires-Dist: requests (~=2.31.0)
Requires-Dist: pydantic (~=2.3.0)
Requires-Dist: urllib3 (==1.26.17)
Requires-Dist: aiofiles (~=23.2.1)
Requires-Dist: setuptools (~=65.5.1)
Requires-Dist: tiktoken (~=0.5.1)
Requires-Dist: python-dotenv (==1.0.0)
Requires-Dist: SpeechRecognition (==3.10.0)
Requires-Dist: browser-cookie3 (==0.19.1)
